{
  "parent": "mekanism:main/enrichment_chamber",
  "display": {
    "icon": {"item": "mekanism:dust_obsidian"},
    "title": {"translate": "advancement.mek.obsidian_dust"},
    "description": {"translate": "advancement.mek.obsidian_dust.desc"},
    "hidden": false,
    "frame": "task",
    "show_toast": "true",
    "announced_to_chat": true
  },
  "criteria": {
    "craft": {
      "trigger": "minecraft:inventory_changed",
      "conditions": {
        "items": [
          {"item": "mekanism:dust_obsidian"}
        ]
      }
    }
  },
  "requirements": [
    [
      "craft"
    ]
  ]
}